{
  "hash": "7ca547bb5ee5a0484de6968466a01883",
  "result": {
    "markdown": "---\ntitle: \"Chapter 1 Day 1\"\nformat: \n  html: \n    embed-resources: true\n---\n\n\n::: panel-tabset\n## Lecture\n\n\n\nThis is a draft of chapter 1's Day 1\n\n### Concept 1\n\n### Example 1\n\n::: {.cell}\n\n```{.r .cell-code}\n1 + 1\n```\n\n::: {.cell-output .cell-output-stdout}\n```\n[1] 2\n```\n:::\n:::\n\n\n\n## Homework\n\n2 different ways to link to homework download\n\n\nThis will download the file but will give it the specified name.\n::: callout-note\n<a href=\"https://tbrost.github.io/BYUI-Timeseries-Drafts/chapter_1/Chapter_1_1_HW.qmd\" download=\"Ch1D1-HW.qmd\"> Chapter 1 Day 1 Homework </a>\n:::\n\nThis will just download the file as named in the hosting repository.\n<a href=\"https://tbrost.github.io/BYUI-Timeseries-Drafts/chapter_1/Chapter_1_1_HW.qmd\">Click To Download</a>\n\nIf you place the completed html file in your chapter_1 folder this will link to your completed assignment [Example Link](Ch1D1-HW.html)\n:::\n",
    "supporting": [
      "Chapter_1_1_files"
    ],
    "filters": [
      "rmarkdown/pagebreak.lua"
    ],
    "includes": {},
    "engineDependencies": {},
    "preserve": {},
    "postProcess": true
  }
}