{
  "hash": "ae642f16b88b4de1100c8cab0c3cd132",
  "result": {
    "markdown": "---\ntitle: \"Chapter 1 Day 2\"\nformat: \n  html: \n    embed-resources: true\n---\n\n\n::: panel-tabset\n## Lecture\n\n---\ntitle: \"Chapter 1 Day 1\"\n---\n\nThis is a draft of chapter 1's Day 1\n\n### Concept 1\n\n### Example 1\n\n::: {.cell}\n\n```{.r .cell-code}\n1 + 1\n```\n\n::: {.cell-output .cell-output-stdout}\n```\n[1] 2\n```\n:::\n:::\n\n\n\n## Homework\n\n---\ntitle: \"Chapter 1 Day 1\"\n---\n\nThis is a draft of chapter 1's Day 1\n\n### Question 1\n\n### Example 1\n\n::: {.cell}\n\n```{.r .cell-code}\n1 + 1\n```\n\n::: {.cell-output .cell-output-stdout}\n```\n[1] 2\n```\n:::\n:::\n\n\n:::\n",
    "supporting": [
      "Chapter_1_2_files"
    ],
    "filters": [
      "rmarkdown/pagebreak.lua"
    ],
    "includes": {},
    "engineDependencies": {},
    "preserve": {},
    "postProcess": true
  }
}